{
  "brand": "SCORE STORE",
  "currency": "MXN",
  "updatedAt": "2026-02-14",
  "sections": [
    {
      "id": "BAJA_1000",
      "title": "BAJA 1000",
      "subtitle": "Edición Oficial"
    },
    {
      "id": "BAJA_500",
      "title": "BAJA 500",
      "subtitle": "Edición Oficial"
    },
    {
      "id": "BAJA_400",
      "title": "BAJA 400",
      "subtitle": "Edición Oficial"
    },
    {
      "id": "SF_250",
      "title": "SAN FELIPE 250",
      "subtitle": "Edición Oficial"
    }
  ],
  "products": [
    {
      "id": "b1k-tee-white",
      "name": "Camiseta Blanca BAJA 1000",
      "baseMXN": 450,
      "sectionId": "BAJA_1000",
      "subSection": "Camisetas",
      "tagline": "Edición oficial",
      "sizes": [
        "S",
        "M",
        "L",
        "XL",
        "XXL"
      ],
      "img": "/assets/EDICION_2025/camiseta-blanca-baja1000.webp",
      "images": [
        "/assets/EDICION_2025/camiseta-blanca-baja1000.webp",
        "/assets/EDICION_2025/camiseta-blanca-baja1000-detalle.webp",
        "/assets/EDICION_2025/camiseta-blanca-baja1000-atras.webp"
      ],
      "stock": 24
    },
    {
      "id": "b1k-tee-grey",
      "name": "Camiseta Gris BAJA 1000",
      "baseMXN": 450,
      "sectionId": "BAJA_1000",
      "subSection": "Camisetas",
      "tagline": "Edición oficial",
      "sizes": [
        "S",
        "M",
        "L",
        "XL",
        "XXL"
      ],
      "img": "/assets/EDICION_2025/camiseta-gris-baja1000.webp",
      "images": [
        "/assets/EDICION_2025/camiseta-gris-baja1000.webp",
        "/assets/EDICION_2025/camiseta-gris-baja1000-detalle.webp",
        "/assets/EDICION_2025/camiseta-gris-baja1000-atras.webp"
      ],
      "stock": 18
    },
    {
      "id": "b1k-jacket",
      "name": "Chamarra BAJA 1000",
      "baseMXN": 1250,
      "sectionId": "BAJA_1000",
      "subSection": "Jackets",
      "tagline": "Corte premium",
      "sizes": [
        "S",
        "M",
        "L",
        "XL",
        "XXL"
      ],
      "img": "/assets/EDICION_2025/chamarra-baja1000.webp",
      "images": [
        "/assets/EDICION_2025/chamarra-baja1000.webp",
        "/assets/EDICION_2025/chamarra-baja1000-detalle.webp"
      ],
      "stock": 10
    },
    {
      "id": "b1k-hoodie-blk",
      "name": "Hoodie Negra BAJA 1000",
      "baseMXN": 850,
      "sectionId": "BAJA_1000",
      "subSection": "Hoodies",
      "tagline": "Edición oficial",
      "sizes": [
        "S",
        "M",
        "L",
        "XL",
        "XXL"
      ],
      "img": "/assets/OTRAS_EDICIONES/hoodie-negra-baja1000.webp",
      "images": [
        "/assets/OTRAS_EDICIONES/hoodie-negra-baja1000.webp"
      ],
      "stock": 12
    },
    {
      "id": "b1k-hoodie-red-blk",
      "name": "Hoodie Negra/Roja BAJA 1000",
      "baseMXN": 950,
      "sectionId": "BAJA_1000",
      "subSection": "Hoodies",
      "tagline": "Edición especial",
      "sizes": [
        "S",
        "M",
        "L",
        "XL",
        "XXL"
      ],
      "img": "/assets/OTRAS_EDICIONES/hoodie-negra-roja-baja1000.webp",
      "images": [
        "/assets/OTRAS_EDICIONES/hoodie-negra-roja-baja1000.webp",
        "/assets/OTRAS_EDICIONES/hoodie-negra-roja-baja1000-detalle.webp"
      ],
      "stock": 8
    },
    {
      "id": "b1k-shirt-pits-grey",
      "name": "Camisa Pits Gris BAJA 1000",
      "baseMXN": 780,
      "sectionId": "BAJA_1000",
      "subSection": "Camisas",
      "tagline": "Look pits / crew",
      "sizes": [
        "S",
        "M",
        "L",
        "XL",
        "XXL"
      ],
      "img": "/assets/EDICION_2025/camisa-gris-pits-baja1000.jpg.webp",
      "images": [
        "/assets/EDICION_2025/camisa-gris-pits-baja1000.jpg.webp",
        "/assets/EDICION_2025/camisa-gris-pits-baja1000-detalles.jpg.webp"
      ],
      "stock": 14
    },
    {
      "id": "b1k-shirt-pits-black",
      "name": "Camisa Pits Negra BAJA 1000",
      "baseMXN": 780,
      "sectionId": "BAJA_1000",
      "subSection": "Camisas",
      "tagline": "Look pits / crew",
      "sizes": [
        "S",
        "M",
        "L",
        "XL",
        "XXL"
      ],
      "img": "/assets/EDICION_2025/camisa-negra-pits-baja1000.webp",
      "images": [
        "/assets/EDICION_2025/camisa-negra-pits-baja1000.webp",
        "/assets/EDICION_2025/camisa-negra-pits-baja1000-detalle.webp"
      ],
      "stock": 9
    },
    {
      "id": "b1k-cap",
      "name": "Gorra BAJA 1000 (Roja/Gris)",
      "baseMXN": 350,
      "sectionId": "BAJA_1000",
      "subSection": "Gorras",
      "tagline": "Edición oficial",
      "sizes": [
        "Unitalla"
      ],
      "img": "/assets/EDICION_2025/gorras-roja-gris.webp",
      "images": [
        "/assets/EDICION_2025/gorras-roja-gris.webp"
      ],
      "stock": 30
    },
    {
      "id": "b500-tee-grey",
      "name": "Camiseta Gris BAJA 500",
      "baseMXN": 450,
      "sectionId": "BAJA_500",
      "subSection": "Camisetas",
      "tagline": "Edición oficial",
      "sizes": [
        "S",
        "M",
        "L",
        "XL",
        "XXL"
      ],
      "img": "/assets/BAJA500/camiseta-gris-baja500.webp",
      "images": [
        "/assets/BAJA500/camiseta-gris-baja500.webp",
        "/assets/EDICION_2025/camiseta-gris-baja500-detalle.webp",
        "/assets/EDICION_2025/camiseta-gris-baja500-atras.webp"
      ],
      "stock": 16
    },
    {
      "id": "b400-tee-brown",
      "name": "Camiseta Café BAJA 400",
      "baseMXN": 450,
      "sectionId": "BAJA_400",
      "subSection": "Camisetas",
      "tagline": "Edición oficial",
      "sizes": [
        "S",
        "M",
        "L",
        "XL",
        "XXL"
      ],
      "img": "/assets/BAJA400/camiseta-cafe- oscuro-baja400.webp",
      "images": [
        "/assets/BAJA400/camiseta-cafe- oscuro-baja400.webp"
      ],
      "stock": 20
    },
    {
      "id": "sf250-tee-brown",
      "name": "Camiseta Café SAN FELIPE 250",
      "baseMXN": 450,
      "sectionId": "SF_250",
      "subSection": "Camisetas",
      "tagline": "Edición oficial",
      "sizes": [
        "S",
        "M",
        "L",
        "XL",
        "XXL"
      ],
      "img": "/assets/SF250/camiseta-cafe-oscuro-sf250.webp",
      "images": [
        "/assets/SF250/camiseta-cafe-oscuro-sf250.webp"
      ],
      "stock": 22
    }
  ]
}